enet.cpython-39-x86_64-linux-gnu.so
pyenet-1.3.17.dist-info/RECORD
pyenet-1.3.17.dist-info/METADATA
pyenet-1.3.17.dist-info/WHEEL
pyenet-1.3.17.dist-info/top_level.txt
pyenet-1.3.17.dist-info/LICENSE
