Metadata-Version: 2.1
Name: pyenet
Version: 1.3.17
Summary: A python wrapper for the ENet library
Home-page: https://github.com/piqueserver/pyenet/
Maintainer: Andrew Resch, Piqueserver team
Maintainer-email: samuel@swalladge.id.au
License-File: LICENSE
Requires-Dist: Cython<1,>=0
